generate_tiff_offsets/__init__.py
generate_tiff_offsets/_version.py
generate_tiff_offsets/cli.py
generate_tiff_offsets/generate_tiff_offsets.py
generate_tiff_offsets-0.1.9.dist-info/METADATA
generate_tiff_offsets-0.1.9.dist-info/WHEEL
generate_tiff_offsets-0.1.9.dist-info/licenses/LICENSE
generate_tiff_offsets-0.1.9.dist-info/RECORD
