Metadata-Version: 2.3
Name: generate-tiff-offsets
Version: 0.1.9
Summary: A package to generate TIFF offsets
Author-email: Ilan Gold <ilan.gold@helmholtz-munich.de>
License: MIT
Classifier: Environment :: Console
Classifier: Framework :: Jupyter
Classifier: Intended Audience :: Developers
Classifier: Intended Audience :: Science/Research
Classifier: Natural Language :: English
Classifier: Operating System :: MacOS :: MacOS X
Classifier: Operating System :: Microsoft :: Windows
Classifier: Operating System :: POSIX :: Linux
Classifier: Programming Language :: Python :: 3
Classifier: Programming Language :: Python :: 3.10
Classifier: Programming Language :: Python :: 3.11
Classifier: Programming Language :: Python :: 3.12
Classifier: Topic :: Scientific/Engineering :: Bio-Informatics
Classifier: Topic :: Scientific/Engineering :: Visualization
Requires-Python: >=3.10
Requires-Dist: tifffile>=2023.9.26
Provides-Extra: test
Requires-Dist: pytest; extra == 'test'
